{
    "data": {
        "_id": "5f1bd59b338f77693081203b",
        "name": "BUBUK KOPI SUPER ARABICA 100% KOPI SIDIKALANG SUMUT",
        "url": "https://www.tokopedia.com/hancook/bubuk-kopi-super-arabica-100-kopi-sidikalang-sumut-1",
        "imageUrl": "https://ecs7.tokopedia.net/img/cache/200-square/product-1/2019/8/6/5996034/5996034_41997048-0473-45b9-afd4-e8414e566b1c_800_800.webp",
        "storeName": "HANCOOK STORE",
        "initialPrice": 44000,
        "currentPrice": 44000,
        "history": [
          {
            "time": "2020-07-25T06:47:55.976Z",
            "price": 44000,
            "stock": ""
          },
          {
            "time": "2020-07-25T06:48:01.599Z",
            "price": 44000,
            "stock": ""
          },
          {
            "time": "2020-07-25T06:48:21.521Z",
            "price": 44000,
            "stock": ""
          },
          {
            "time": "2020-07-25T06:48:41.798Z",
            "price": 44000,
            "stock": ""
          },
          {
            "time": "2020-07-25T06:49:01.238Z",
            "price": 44000,
            "stock": ""
          },
          {
            "time": "2020-07-25T06:49:21.357Z",
            "price": 44000,
            "stock": ""
          },
          {
            "time": "2020-07-25T06:49:41.504Z",
            "price": 44000,
            "stock": ""
          },
          {
            "time": "2020-07-25T06:50:01.729Z",
            "price": 44000,
            "stock": ""
          },
          {
            "time": "2020-07-25T06:50:21.168Z",
            "price": 44000,
            "stock": ""
          },
          {
            "time": "2020-07-25T06:50:41.423Z",
            "price": 44000,
            "stock": ""
          },
          {
            "time": "2020-07-25T06:51:01.454Z",
            "price": 44000,
            "stock": ""
          },
          {
            "time": "2020-07-25T06:51:21.979Z",
            "price": 44000,
            "stock": ""
          },
          {
            "time": "2020-07-25T06:51:41.137Z",
            "price": 44000,
            "stock": ""
          },
          {
            "time": "2020-07-25T06:52:00.767Z",
            "price": 44000,
            "stock": ""
          },
          {
            "time": "2020-07-25T06:52:21.128Z",
            "price": 44000,
            "stock": ""
          },
          {
            "time": "2020-07-25T06:52:40.644Z",
            "price": 44000,
            "stock": ""
          },
          {
            "time": "2020-07-25T06:53:00.705Z",
            "price": 44000,
            "stock": ""
          },
          {
            "time": "2020-07-25T06:53:20.706Z",
            "price": 44000,
            "stock": ""
          },
          {
            "time": "2020-07-25T06:53:40.722Z",
            "price": 44000,
            "stock": ""
          },
          {
            "time": "2020-07-25T06:54:00.720Z",
            "price": 44000,
            "stock": ""
          },
          {
            "time": "2020-07-25T06:54:20.724Z",
            "price": 44000,
            "stock": ""
          },
          {
            "time": "2020-07-25T06:54:41.063Z",
            "price": 44000,
            "stock": ""
          },
          {
            "time": "2020-07-25T06:55:00.669Z",
            "price": 44000,
            "stock": ""
          },
          {
            "time": "2020-07-25T06:55:20.869Z",
            "price": 44000,
            "stock": ""
          },
          {
            "time": "2020-07-25T06:55:40.949Z",
            "price": 44000,
            "stock": ""
          },
          {
            "time": "2020-07-25T06:56:02.158Z",
            "price": 44000,
            "stock": ""
          },
          {
            "time": "2020-07-25T06:56:21.295Z",
            "price": 44000,
            "stock": ""
          },
          {
            "time": "2020-07-25T06:56:41.077Z",
            "price": 44000,
            "stock": ""
          },
          {
            "time": "2020-07-25T06:57:01.376Z",
            "price": 44000,
            "stock": ""
          },
          {
            "time": "2020-07-25T06:57:20.705Z",
            "price": 44000,
            "stock": ""
          },
          {
            "time": "2020-07-25T06:57:40.612Z",
            "price": 44000,
            "stock": ""
          },
          {
            "time": "2020-07-25T06:58:00.596Z",
            "price": 44000,
            "stock": ""
          },
          {
            "time": "2020-07-25T06:58:21.286Z",
            "price": 44000,
            "stock": ""
          },
          {
            "time": "2020-07-25T06:58:41.105Z",
            "price": 44000,
            "stock": ""
          },
          {
            "time": "2020-07-25T06:59:00.747Z",
            "price": 44000,
            "stock": ""
          },
          {
            "time": "2020-07-25T06:59:20.779Z",
            "price": 44000,
            "stock": ""
          },
          {
            "time": "2020-07-25T06:59:40.856Z",
            "price": 44000,
            "stock": ""
          },
          {
            "time": "2020-07-25T07:00:00.928Z",
            "price": 44000,
            "stock": ""
          },
          {
            "time": "2020-07-25T07:00:21.110Z",
            "price": 44000,
            "stock": ""
          },
          {
            "time": "2020-07-25T07:00:41.520Z",
            "price": 44000,
            "stock": ""
          },
          {
            "time": "2020-07-25T07:01:01.149Z",
            "price": 44000,
            "stock": ""
          },
          {
            "time": "2020-07-25T07:01:21.657Z",
            "price": 44000,
            "stock": ""
          },
          {
            "time": "2020-07-25T07:01:41.548Z",
            "price": 44000,
            "stock": ""
          },
          {
            "time": "2020-07-25T07:02:01.436Z",
            "price": 44000,
            "stock": ""
          },
          {
            "time": "2020-07-25T07:02:21.113Z",
            "price": 44000,
            "stock": ""
          },
          {
            "time": "2020-07-25T07:02:41.293Z",
            "price": 44000,
            "stock": ""
          },
          {
            "time": "2020-07-25T07:03:01.461Z",
            "price": 44000,
            "stock": ""
          },
          {
            "time": "2020-07-25T07:03:21.120Z",
            "price": 44000,
            "stock": ""
          },
          {
            "time": "2020-07-25T07:03:41.102Z",
            "price": 44000,
            "stock": ""
          },
          {
            "time": "2020-07-25T07:04:01.211Z",
            "price": 44000,
            "stock": ""
          },
          {
            "time": "2020-07-25T07:04:21.114Z",
            "price": 44000,
            "stock": ""
          },
          {
            "time": "2020-07-25T07:04:41.306Z",
            "price": 44000,
            "stock": ""
          },
          {
            "time": "2020-07-25T07:05:00.888Z",
            "price": 44000,
            "stock": ""
          },
          {
            "time": "2020-07-25T07:05:20.677Z",
            "price": 44000,
            "stock": ""
          },
          {
            "time": "2020-07-25T07:05:40.786Z",
            "price": 44000,
            "stock": ""
          },
          {
            "time": "2020-07-25T07:06:00.741Z",
            "price": 44000,
            "stock": ""
          },
          {
            "time": "2020-07-25T07:06:20.705Z",
            "price": 44000,
            "stock": ""
          },
          {
            "time": "2020-07-25T07:06:41.415Z",
            "price": 44000,
            "stock": ""
          },
          {
            "time": "2020-07-25T07:07:00.752Z",
            "price": 44000,
            "stock": ""
          },
          {
            "time": "2020-07-25T07:07:20.762Z",
            "price": 44000,
            "stock": ""
          },
          {
            "time": "2020-07-25T07:07:41.010Z",
            "price": 44000,
            "stock": ""
          },
          {
            "time": "2020-07-25T07:08:00.725Z",
            "price": 49000,
            "stock": ""
          },
          {
            "time": "2020-07-25T07:08:20.953Z",
            "price": 44000,
            "stock": ""
          },
          {
            "time": "2020-07-25T07:08:41.000Z",
            "price": 42000,
            "stock": ""
          },
          {
            "time": "2020-07-25T07:09:01.700Z",
            "price": 44000,
            "stock": ""
          },
          {
            "time": "2020-07-25T07:09:21.203Z",
            "price": 49000,
            "stock": ""
          },
          {
            "time": "2020-07-25T07:09:41.485Z",
            "price": 44000,
            "stock": ""
          },
          {
            "time": "2020-07-25T07:10:01.413Z",
            "price": 38000,
            "stock": ""
          }
        ],
        "targetPrice": null,
        "email": null,
        "createdAt": "2020-07-25T06:47:55.975Z",
        "current_price": 44000
      }
}